{"backend_index.md":"DuUJIpw0","backend_java.md":"CtWFZR1d","backend_mysql.md":"CIo_67VF","backend_nginx.md":"DDNs7LiJ","backend_linux.md":"BFVsNBg7","backend_php_advanced.md":"Dgi1fBmx","backend_php_fpdf.md":"nkwjoA7o","backend_php_basic.md":"Bj8NAiWm","backend_vim.md":"D3M72qhb","backend_php_phpword.md":"BaOOFWAB","backend_redis.md":"BvyVFQGi","backend_php_laravel.md":"CE9qzHpa","frontend_index.md":"D771zZls","frontend_html.md":"B3em-j-D","frontend_nodejs.md":"CmM4WfS0","frontend_typescript.md":"BzIcz8J0","index.md":"BWcEg4QY","notes_app_guides.md":"ClcHUEkl","notes_cli_tools.md":"Do0z9k5z","frontend_vue3.md":"BYV6zS7V","notes_docker.md":"7nmZQesC","notes_index.md":"CVEPYkxH","notes_git.md":"a5-sP0lN","notes_mac.md":"B3cqgx-t","notes_vscode.md":"CXknQ6Ov","notes_software.md":"BjI3chkG"}
